<?xml version='1.0' encoding='UTF-8'?>
<rdf:RDF xmlns:rdf='http://www.w3.org/1999/02/22-rdf-syntax-ns#'>

<rdf:Description rdf:about='GH018426.MP4'
  xmlns:et='http://ns.exiftool.ca/1.0/' et:toolkit='Image::ExifTool 12.10'
  xmlns:ExifTool='http://ns.exiftool.ca/ExifTool/1.0/'
  xmlns:System='http://ns.exiftool.ca/File/System/1.0/'
  xmlns:File='http://ns.exiftool.ca/File/1.0/'
  xmlns:QuickTime='http://ns.exiftool.ca/QuickTime/QuickTime/1.0/'
  xmlns:UserData='http://ns.exiftool.ca/QuickTime/UserData/1.0/'
  xmlns:GoPro='http://ns.exiftool.ca/QuickTime/GoPro/1.0/'
  xmlns:Track1='http://ns.exiftool.ca/QuickTime/Track1/1.0/'
  xmlns:Track2='http://ns.exiftool.ca/QuickTime/Track2/1.0/'
  xmlns:Track3='http://ns.exiftool.ca/QuickTime/Track3/1.0/'
  xmlns:Track4='http://ns.exiftool.ca/QuickTime/Track4/1.0/'
  xmlns:Composite='http://ns.exiftool.ca/Composite/1.0/'>
 <ExifTool:ExifToolVersion>12.10</ExifTool:ExifToolVersion>
 <System:FileName>GH018426.MP4</System:FileName>
 <System:Directory>.</System:Directory>
 <System:FileSize>7.0 MB</System:FileSize>
 <System:FileModifyDate>2021:09:15 13:48:33+01:00</System:FileModifyDate>
 <System:FileAccessDate>2021:09:15 13:54:17+01:00</System:FileAccessDate>
 <System:FileInodeChangeDate>2021:09:15 16:41:31+01:00</System:FileInodeChangeDate>
 <System:FilePermissions>rwxrwxrwx</System:FilePermissions>
 <File:FileType>MP4</File:FileType>
 <File:FileTypeExtension>mp4</File:FileTypeExtension>
 <File:MIMEType>video/mp4</File:MIMEType>
 <QuickTime:MajorBrand>MP4 v1 [ISO 14496-1:ch13]</QuickTime:MajorBrand>
 <QuickTime:MinorVersion>2013.10.18</QuickTime:MinorVersion>
 <QuickTime:CompatibleBrands>
  <rdf:Bag>
   <rdf:li>mp41</rdf:li>
  </rdf:Bag>
 </QuickTime:CompatibleBrands>
 <QuickTime:MediaDataSize>7350396</QuickTime:MediaDataSize>
 <QuickTime:MediaDataOffset>28</QuickTime:MediaDataOffset>
 <QuickTime:MovieHeaderVersion>0</QuickTime:MovieHeaderVersion>
 <QuickTime:CreateDate>2021:09:15 13:48:23</QuickTime:CreateDate>
 <QuickTime:ModifyDate>2021:09:15 13:48:23</QuickTime:ModifyDate>
 <QuickTime:TimeScale>90000</QuickTime:TimeScale>
 <QuickTime:Duration>0.90 s</QuickTime:Duration>
 <QuickTime:PreferredRate>1</QuickTime:PreferredRate>
 <QuickTime:PreferredVolume>100.00%</QuickTime:PreferredVolume>
 <QuickTime:MatrixStructure>1 0 0 0 1 0 0 0 1</QuickTime:MatrixStructure>
 <QuickTime:PreviewTime>0 s</QuickTime:PreviewTime>
 <QuickTime:PreviewDuration>0 s</QuickTime:PreviewDuration>
 <QuickTime:PosterTime>0 s</QuickTime:PosterTime>
 <QuickTime:SelectionTime>0 s</QuickTime:SelectionTime>
 <QuickTime:SelectionDuration>0 s</QuickTime:SelectionDuration>
 <QuickTime:CurrentTime>0 s</QuickTime:CurrentTime>
 <QuickTime:NextTrackID>5</QuickTime:NextTrackID>
 <UserData:FirmwareVersion>H19.03.02.00.00</UserData:FirmwareVersion>
 <UserData:LensSerialNumber rdf:datatype='http://www.w3.org/2001/XMLSchema#base64Binary'>
QzMzNjEzQjI1NTIzODgxAAAAAAAAAAAAAAAAAAAAAAAAAAAAAAAAAAAAAAAA
AAAA
</UserData:LensSerialNumber>
 <UserData:SerialNumberHash>43369b5d7335903ecf8fdbbe81a3d1fb</UserData:SerialNumberHash>
 <GoPro:DeviceName>Global Settings</GoPro:DeviceName>
 <GoPro:MetadataVersion>8.1.2</GoPro:MetadataVersion>
 <GoPro:FirmwareVersion>H19.03.02.00.00</GoPro:FirmwareVersion>
 <GoPro:CameraSerialNumber>C3351324612139</GoPro:CameraSerialNumber>
 <GoPro:Model>GoPro Max</GoPro:Model>
 <GoPro:AutoRotation>Up</GoPro:AutoRotation>
 <GoPro:DigitalZoom>No</GoPro:DigitalZoom>
 <GoPro:ProTune>On</GoPro:ProTune>
 <GoPro:WhiteBalance>AUTO</GoPro:WhiteBalance>
 <GoPro:Sharpness>HIGH</GoPro:Sharpness>
 <GoPro:ColorMode>GOPRO</GoPro:ColorMode>
 <GoPro:AutoISOMax>1600</GoPro:AutoISOMax>
 <GoPro:AutoISOMin>100</GoPro:AutoISOMin>
 <GoPro:ExposureCompensation>0.0</GoPro:ExposureCompensation>
 <GoPro:Rate>AUTO</GoPro:Rate>
 <GoPro:FieldOfView>Wide</GoPro:FieldOfView>
 <GoPro:ElectronicImageStabilization>HS EIS</GoPro:ElectronicImageStabilization>
 <GoPro:AudioSetting>STEREO</GoPro:AudioSetting>
 <GoPro:DeviceName>Geometry Calibrations</GoPro:DeviceName>
 <GoPro:DeviceName>Back Lens</GoPro:DeviceName>
 <GoPro:DeviceName>Front Lens</GoPro:DeviceName>
 <GoPro:DeviceName>Highlights</GoPro:DeviceName>
 <Track1:TrackHeaderVersion>0</Track1:TrackHeaderVersion>
 <Track1:TrackCreateDate>2021:09:15 13:48:23</Track1:TrackCreateDate>
 <Track1:TrackModifyDate>2021:09:15 13:48:23</Track1:TrackModifyDate>
 <Track1:TrackID>1</Track1:TrackID>
 <Track1:TrackDuration>0.90 s</Track1:TrackDuration>
 <Track1:TrackLayer>0</Track1:TrackLayer>
 <Track1:TrackVolume>0.00%</Track1:TrackVolume>
 <Track1:MatrixStructure>1 0 0 0 1 0 0 0 1</Track1:MatrixStructure>
 <Track1:ImageWidth>1920</Track1:ImageWidth>
 <Track1:ImageHeight>1080</Track1:ImageHeight>
 <Track1:TimeCode>2</Track1:TimeCode>
 <Track1:MediaHeaderVersion>0</Track1:MediaHeaderVersion>
 <Track1:MediaCreateDate>2021:09:15 13:48:23</Track1:MediaCreateDate>
 <Track1:MediaModifyDate>2021:09:15 13:48:23</Track1:MediaModifyDate>
 <Track1:MediaTimeScale>90000</Track1:MediaTimeScale>
 <Track1:MediaDuration>0.90 s</Track1:MediaDuration>
 <Track1:HandlerClass>Media Handler</Track1:HandlerClass>
 <Track1:HandlerType>Video Track</Track1:HandlerType>
 <Track1:HandlerDescription>GoPro AVC  </Track1:HandlerDescription>
 <Track1:GraphicsMode>srcCopy</Track1:GraphicsMode>
 <Track1:OpColor>0 0 0</Track1:OpColor>
 <Track1:CompressorID>avc1</Track1:CompressorID>
 <Track1:SourceImageWidth>1920</Track1:SourceImageWidth>
 <Track1:SourceImageHeight>1080</Track1:SourceImageHeight>
 <Track1:XResolution>72</Track1:XResolution>
 <Track1:YResolution>72</Track1:YResolution>
 <Track1:CompressorName>GoPro AVC encoder</Track1:CompressorName>
 <Track1:BitDepth>24</Track1:BitDepth>
 <Track1:ColorRepresentation>nclx 1 1 1</Track1:ColorRepresentation>
 <Track1:VideoFrameRate>29.97</Track1:VideoFrameRate>
 <Track2:TrackHeaderVersion>0</Track2:TrackHeaderVersion>
 <Track2:TrackCreateDate>2021:09:15 13:48:23</Track2:TrackCreateDate>
 <Track2:TrackModifyDate>2021:09:15 13:48:23</Track2:TrackModifyDate>
 <Track2:TrackID>2</Track2:TrackID>
 <Track2:TrackDuration>0.90 s</Track2:TrackDuration>
 <Track2:TrackLayer>0</Track2:TrackLayer>
 <Track2:TrackVolume>0.00%</Track2:TrackVolume>
 <Track2:MatrixStructure>1 0 0 0 1 0 0 0 1</Track2:MatrixStructure>
 <Track2:ImageWidth>1920</Track2:ImageWidth>
 <Track2:ImageHeight>16</Track2:ImageHeight>
 <Track2:MediaHeaderVersion>0</Track2:MediaHeaderVersion>
 <Track2:MediaCreateDate>2021:09:15 13:48:23</Track2:MediaCreateDate>
 <Track2:MediaModifyDate>2021:09:15 13:48:23</Track2:MediaModifyDate>
 <Track2:MediaTimeScale>90000</Track2:MediaTimeScale>
 <Track2:MediaDuration>0.90 s</Track2:MediaDuration>
 <Track2:HandlerClass>Media Handler</Track2:HandlerClass>
 <Track2:HandlerType>Time Code</Track2:HandlerType>
 <Track2:HandlerDescription>GoPro TCD  </Track2:HandlerDescription>
 <Track2:GenMediaVersion>0</Track2:GenMediaVersion>
 <Track2:GenFlags>0 0 0</Track2:GenFlags>
 <Track2:GenGraphicsMode>ditherCopy</Track2:GenGraphicsMode>
 <Track2:GenOpColor>32768 32768 32768</Track2:GenOpColor>
 <Track2:GenBalance>0</Track2:GenBalance>
 <Track2:TextFont>Unknown (21)</Track2:TextFont>
 <Track2:TextFace>Plain</Track2:TextFace>
 <Track2:TextSize>10</Track2:TextSize>
 <Track2:TextColor>0 0 0</Track2:TextColor>
 <Track2:BackgroundColor>65535 65535 65535</Track2:BackgroundColor>
 <Track2:FontName>Helvetica</Track2:FontName>
 <Track2:OtherFormat>tmcd</Track2:OtherFormat>
 <Track3:TrackHeaderVersion>0</Track3:TrackHeaderVersion>
 <Track3:TrackCreateDate>2021:09:15 13:48:23</Track3:TrackCreateDate>
 <Track3:TrackModifyDate>2021:09:15 13:48:23</Track3:TrackModifyDate>
 <Track3:TrackID>3</Track3:TrackID>
 <Track3:TrackDuration>9.34 s</Track3:TrackDuration>
 <Track3:TrackLayer>0</Track3:TrackLayer>
 <Track3:TrackVolume>0.00%</Track3:TrackVolume>
 <Track3:MatrixStructure>1 0 0 0 1 0 0 0 1</Track3:MatrixStructure>
 <Track3:MediaHeaderVersion>0</Track3:MediaHeaderVersion>
 <Track3:MediaCreateDate>2021:09:15 13:48:23</Track3:MediaCreateDate>
 <Track3:MediaModifyDate>2021:09:15 13:48:23</Track3:MediaModifyDate>
 <Track3:MediaTimeScale>10000</Track3:MediaTimeScale>
 <Track3:MediaDuration>0.93 s</Track3:MediaDuration>
 <Track3:HandlerClass>Media Handler</Track3:HandlerClass>
 <Track3:HandlerType>NRT Metadata</Track3:HandlerType>
 <Track3:HandlerDescription>GoPro MET  </Track3:HandlerDescription>
 <Track3:GenMediaVersion>0</Track3:GenMediaVersion>
 <Track3:GenFlags>0 0 0</Track3:GenFlags>
 <Track3:GenGraphicsMode>srcCopy</Track3:GenGraphicsMode>
 <Track3:GenOpColor>0 0 0</Track3:GenOpColor>
 <Track3:GenBalance>0</Track3:GenBalance>
 <Track3:MetaFormat>gpmd</Track3:MetaFormat>
 <Track3:SampleTime>0 s</Track3:SampleTime>
 <Track3:SampleDuration>0.03 s</Track3:SampleDuration>
 <Track3:DeviceName>GoPro Max</Track3:DeviceName>
 <Track3:TimeStamp>0.016074</Track3:TimeStamp>
 <Track3:CameraTemperature>26.341796875 C</Track3:CameraTemperature>
 <Track3:Accelerometer>(Binary data 54 bytes, use -b option to extract)</Track3:Accelerometer>
 <Track3:TimeStamp>0.016074</Track3:TimeStamp>
 <Track3:CameraTemperature>26.341796875 C</Track3:CameraTemperature>
 <Track3:Gyroscope>(Binary data 59 bytes, use -b option to extract)</Track3:Gyroscope>
 <Track3:TimeStamp>0.05396</Track3:TimeStamp>
 <Track3:Magnetometer>7 25 30</Track3:Magnetometer>
 <Track3:TimeStamp>0.085858</Track3:TimeStamp>
 <Track3:ExposureTimes>1/790</Track3:ExposureTimes>
 <Track3:TimeStamp>0.085858</Track3:TimeStamp>
 <Track3:ColorTemperatures>5983</Track3:ColorTemperatures>
 <Track3:TimeStamp>0.085858</Track3:TimeStamp>
 <Track3:WhiteBalanceRGB>(Binary data 21 bytes, use -b option to extract)</Track3:WhiteBalanceRGB>
 <Track3:TimeStamp>0.085858</Track3:TimeStamp>
 <Track3:ISOSpeeds>100</Track3:ISOSpeeds>
 <Track3:TimeStamp>0.081756</Track3:TimeStamp>
 <Track3:TimeStamp>0.085858</Track3:TimeStamp>
 <Track3:TimeStamp>0.081756</Track3:TimeStamp>
 <Track3:TimeStamp>0.081756</Track3:TimeStamp>
 <Track3:TimeStamp>0.011572</Track3:TimeStamp>
 <Track3:GPSMeasureMode>Unknown (0)</Track3:GPSMeasureMode>
 <Track3:GPSDateTime>2021:09:15 12:46:46.164</Track3:GPSDateTime>
 <Track3:GPSHPositioningError>99.99</Track3:GPSHPositioningError>
 <Track3:GPSLatitude>51 deg 18&#39; 19.56&quot; N</Track3:GPSLatitude>
 <Track3:GPSLongitude>0 deg 51&#39; 56.24&quot; W</Track3:GPSLongitude>
 <Track3:GPSAltitude>181.321 m</Track3:GPSAltitude>
 <Track3:GPSSpeed>0</Track3:GPSSpeed>
 <Track3:GPSSpeed3D>0</Track3:GPSSpeed3D>
 <Track3:TimeStamp>0.085858</Track3:TimeStamp>
 <Track3:TimeStamp>0.085858</Track3:TimeStamp>
 <Track3:TimeStamp>0.033333</Track3:TimeStamp>
 <Track3:TimeStamp>0.085858</Track3:TimeStamp>
 <Track3:SampleTime>0.03 s</Track3:SampleTime>
 <Track3:SampleDuration>0.03 s</Track3:SampleDuration>
 <Track3:DeviceName>GoPro Max</Track3:DeviceName>
 <Track3:TimeStamp>0.085836</Track3:TimeStamp>
 <Track3:CameraTemperature>26.296875 C</Track3:CameraTemperature>
 <Track3:Accelerometer>(Binary data 54 bytes, use -b option to extract)</Track3:Accelerometer>
 <Track3:TimeStamp>0.085836</Track3:TimeStamp>
 <Track3:CameraTemperature>26.296875 C</Track3:CameraTemperature>
 <Track3:Gyroscope>(Binary data 56 bytes, use -b option to extract)</Track3:Gyroscope>
 <Track3:TimeStamp>0.093829</Track3:TimeStamp>
 <Track3:Magnetometer>5 25 30</Track3:Magnetometer>
 <Track3:TimeStamp>0.119224</Track3:TimeStamp>
 <Track3:ExposureTimes>1/790</Track3:ExposureTimes>
 <Track3:TimeStamp>0.185958</Track3:TimeStamp>
 <Track3:ColorTemperatures>5983</Track3:ColorTemperatures>
 <Track3:TimeStamp>0.185958</Track3:TimeStamp>
 <Track3:WhiteBalanceRGB>(Binary data 21 bytes, use -b option to extract)</Track3:WhiteBalanceRGB>
 <Track3:TimeStamp>0.119224</Track3:TimeStamp>
 <Track3:ISOSpeeds>100</Track3:ISOSpeeds>
 <Track3:TimeStamp>0.186897</Track3:TimeStamp>
 <Track3:TimeStamp>0.185958</Track3:TimeStamp>
 <Track3:TimeStamp>0.081756</Track3:TimeStamp>
 <Track3:TimeStamp>0.081756</Track3:TimeStamp>
 <Track3:TimeStamp>0.070542</Track3:TimeStamp>
 <Track3:GPSMeasureMode>Unknown (0)</Track3:GPSMeasureMode>
 <Track3:GPSDateTime>2021:09:15 12:46:46.164</Track3:GPSDateTime>
 <Track3:GPSHPositioningError>99.99</Track3:GPSHPositioningError>
 <Track3:GPSLatitude>51 deg 18&#39; 19.61&quot; N</Track3:GPSLatitude>
 <Track3:GPSLongitude>0 deg 51&#39; 56.21&quot; W</Track3:GPSLongitude>
 <Track3:GPSAltitude>181.32 m</Track3:GPSAltitude>
 <Track3:GPSSpeed>0</Track3:GPSSpeed>
 <Track3:GPSSpeed3D>0</Track3:GPSSpeed3D>
 <Track3:TimeStamp>0.419525</Track3:TimeStamp>
 <Track3:TimeStamp>0.419525</Track3:TimeStamp>
 <Track3:TimeStamp>0.119191</Track3:TimeStamp>
 <Track3:TimeStamp>0.419525</Track3:TimeStamp>
 <Track3:SampleTime>0.07 s</Track3:SampleTime>
 <Track3:SampleDuration>0.03 s</Track3:SampleDuration>
 <Track3:DeviceName>GoPro Max</Track3:DeviceName>
 <Track3:TimeStamp>0.419697</Track3:TimeStamp>
 <Track3:CameraTemperature>26.333984375 C</Track3:CameraTemperature>
 <Track3:Accelerometer>(Binary data 55 bytes, use -b option to extract)</Track3:Accelerometer>
 <Track3:TimeStamp>0.419697</Track3:TimeStamp>
 <Track3:CameraTemperature>26.333984375 C</Track3:CameraTemperature>
 <Track3:Gyroscope>(Binary data 58 bytes, use -b option to extract)</Track3:Gyroscope>
 <Track3:TimeStamp>0.412781</Track3:TimeStamp>
 <Track3:Magnetometer>4 26 31</Track3:Magnetometer>
 <Track3:TimeStamp>0.419518</Track3:TimeStamp>
 <Track3:ExposureTimes>1/791</Track3:ExposureTimes>
 <Track3:TimeStamp>0.386158</Track3:TimeStamp>
 <Track3:ColorTemperatures>6003</Track3:ColorTemperatures>
 <Track3:TimeStamp>0.386158</Track3:TimeStamp>
 <Track3:WhiteBalanceRGB>(Binary data 29 bytes, use -b option to extract)</Track3:WhiteBalanceRGB>
 <Track3:TimeStamp>0.419518</Track3:TimeStamp>
 <Track3:ISOSpeeds>100</Track3:ISOSpeeds>
 <Track3:TimeStamp>0.391908</Track3:TimeStamp>
 <Track3:TimeStamp>0.386158</Track3:TimeStamp>
 <Track3:TimeStamp>0.391908</Track3:TimeStamp>
 <Track3:TimeStamp>0.391908</Track3:TimeStamp>
 <Track3:TimeStamp>0.429939</Track3:TimeStamp>
 <Track3:GPSMeasureMode>Unknown (0)</Track3:GPSMeasureMode>
 <Track3:GPSDateTime>2021:09:15 12:46:52.104</Track3:GPSDateTime>
 <Track3:GPSHPositioningError>99.99</Track3:GPSHPositioningError>
 <Track3:GPSLatitude>51 deg 18&#39; 19.59&quot; N</Track3:GPSLatitude>
 <Track3:GPSLongitude>0 deg 51&#39; 56.21&quot; W</Track3:GPSLongitude>
 <Track3:GPSAltitude>181.319 m</Track3:GPSAltitude>
 <Track3:GPSSpeed>0</Track3:GPSSpeed>
 <Track3:GPSSpeed3D>0</Track3:GPSSpeed3D>
 <Track3:TimeStamp>0.753192</Track3:TimeStamp>
 <Track3:TimeStamp>0.753192</Track3:TimeStamp>
 <Track3:TimeStamp>0.452858</Track3:TimeStamp>
 <Track3:TimeStamp>0.753192</Track3:TimeStamp>
 <Track3:SampleTime>0.10 s</Track3:SampleTime>
 <Track3:SampleDuration>0.03 s</Track3:SampleDuration>
 <Track3:DeviceName>GoPro Max</Track3:DeviceName>
 <Track3:TimeStamp>0.753558</Track3:TimeStamp>
 <Track3:CameraTemperature>26.396484375 C</Track3:CameraTemperature>
 <Track3:Accelerometer>(Binary data 54 bytes, use -b option to extract)</Track3:Accelerometer>
 <Track3:TimeStamp>0.753558</Track3:TimeStamp>
 <Track3:CameraTemperature>26.396484375 C</Track3:CameraTemperature>
 <Track3:Gyroscope>(Binary data 57 bytes, use -b option to extract)</Track3:Gyroscope>
 <Track3:TimeStamp>0.771602</Track3:TimeStamp>
 <Track3:Magnetometer>3 28 30</Track3:Magnetometer>
 <Track3:TimeStamp>0.753178</Track3:TimeStamp>
 <Track3:ExposureTimes>1/794</Track3:ExposureTimes>
 <Track3:TimeStamp>0.786558</Track3:TimeStamp>
 <Track3:ColorTemperatures>6043</Track3:ColorTemperatures>
 <Track3:TimeStamp>0.786558</Track3:TimeStamp>
 <Track3:WhiteBalanceRGB>(Binary data 19 bytes, use -b option to extract)</Track3:WhiteBalanceRGB>
 <Track3:TimeStamp>0.753178</Track3:TimeStamp>
 <Track3:ISOSpeeds>100</Track3:ISOSpeeds>
 <Track3:TimeStamp>0.79352</Track3:TimeStamp>
 <Track3:TimeStamp>0.786558</Track3:TimeStamp>
 <Track3:TimeStamp>0.79352</Track3:TimeStamp>
 <Track3:TimeStamp>0.79352</Track3:TimeStamp>
 <Track3:TimeStamp>0.860414</Track3:TimeStamp>
 <Track3:GPSMeasureMode>Unknown (0)</Track3:GPSMeasureMode>
 <Track3:GPSDateTime>2021:09:15 12:46:52.159</Track3:GPSDateTime>
 <Track3:GPSHPositioningError>99.99</Track3:GPSHPositioningError>
 <Track3:GPSLatitude>51 deg 18&#39; 19.52&quot; N</Track3:GPSLatitude>
 <Track3:GPSLongitude>0 deg 51&#39; 56.16&quot; W</Track3:GPSLongitude>
 <Track3:GPSAltitude>181.323 m</Track3:GPSAltitude>
 <Track3:GPSSpeed>0</Track3:GPSSpeed>
 <Track3:GPSSpeed3D>0</Track3:GPSSpeed3D>
 <Track3:TimeStamp>1.086858</Track3:TimeStamp>
 <Track3:TimeStamp>1.086858</Track3:TimeStamp>
 <Track3:TimeStamp>0.786525</Track3:TimeStamp>
 <Track3:TimeStamp>1.086858</Track3:TimeStamp>
 <Track3:SampleTime>0.13 s</Track3:SampleTime>
 <Track3:SampleDuration>0.03 s</Track3:SampleDuration>
 <Track3:DeviceName>GoPro Max</Track3:DeviceName>
 <Track3:TimeStamp>1.087419</Track3:TimeStamp>
 <Track3:CameraTemperature>26.404296875 C</Track3:CameraTemperature>
 <Track3:Accelerometer>(Binary data 53 bytes, use -b option to extract)</Track3:Accelerometer>
 <Track3:TimeStamp>1.087419</Track3:TimeStamp>
 <Track3:CameraTemperature>26.404296875 C</Track3:CameraTemperature>
 <Track3:Gyroscope>(Binary data 56 bytes, use -b option to extract)</Track3:Gyroscope>
 <Track3:TimeStamp>1.090554</Track3:TimeStamp>
 <Track3:Magnetometer>3 29 30</Track3:Magnetometer>
 <Track3:TimeStamp>1.086838</Track3:TimeStamp>
 <Track3:ExposureTimes>1/794</Track3:ExposureTimes>
 <Track3:TimeStamp>1.086858</Track3:TimeStamp>
 <Track3:ColorTemperatures>6104</Track3:ColorTemperatures>
 <Track3:TimeStamp>1.086858</Track3:TimeStamp>
 <Track3:WhiteBalanceRGB>(Binary data 22 bytes, use -b option to extract)</Track3:WhiteBalanceRGB>
 <Track3:TimeStamp>1.086838</Track3:TimeStamp>
 <Track3:ISOSpeeds>100</Track3:ISOSpeeds>
 <Track3:TimeStamp>1.108343</Track3:TimeStamp>
 <Track3:TimeStamp>1.086858</Track3:TimeStamp>
 <Track3:TimeStamp>1.108343</Track3:TimeStamp>
 <Track3:TimeStamp>1.108343</Track3:TimeStamp>
 <Track3:TimeStamp>1.106407</Track3:TimeStamp>
 <Track3:GPSMeasureMode>Unknown (0)</Track3:GPSMeasureMode>
 <Track3:GPSDateTime>2021:09:15 12:46:53.204</Track3:GPSDateTime>
 <Track3:GPSHPositioningError>99.99</Track3:GPSHPositioningError>
 <Track3:GPSLatitude>51 deg 18&#39; 20.96&quot; N</Track3:GPSLatitude>
 <Track3:GPSLongitude>0 deg 52&#39; 11.19&quot; W</Track3:GPSLongitude>
 <Track3:GPSAltitude>180.798 m</Track3:GPSAltitude>
 <Track3:GPSSpeed>0</Track3:GPSSpeed>
 <Track3:GPSSpeed3D>0</Track3:GPSSpeed3D>
 <Track3:TimeStamp>1.420525</Track3:TimeStamp>
 <Track3:TimeStamp>1.420525</Track3:TimeStamp>
 <Track3:TimeStamp>1.120191</Track3:TimeStamp>
 <Track3:TimeStamp>1.420525</Track3:TimeStamp>
 <Track3:SampleTime>0.17 s</Track3:SampleTime>
 <Track3:SampleDuration>0.03 s</Track3:SampleDuration>
 <Track3:DeviceName>GoPro Max</Track3:DeviceName>
 <Track3:TimeStamp>1.42128</Track3:TimeStamp>
 <Track3:CameraTemperature>26.4375 C</Track3:CameraTemperature>
 <Track3:Accelerometer>(Binary data 53 bytes, use -b option to extract)</Track3:Accelerometer>
 <Track3:TimeStamp>1.42128</Track3:TimeStamp>
 <Track3:CameraTemperature>26.4375 C</Track3:CameraTemperature>
 <Track3:Gyroscope>(Binary data 53 bytes, use -b option to extract)</Track3:Gyroscope>
 <Track3:TimeStamp>1.409506</Track3:TimeStamp>
 <Track3:Magnetometer>4 29 30</Track3:Magnetometer>
 <Track3:TimeStamp>1.420498</Track3:TimeStamp>
 <Track3:ExposureTimes>1/790</Track3:ExposureTimes>
 <Track3:TimeStamp>1.387158</Track3:TimeStamp>
 <Track3:ColorTemperatures>6104</Track3:ColorTemperatures>
 <Track3:TimeStamp>1.387158</Track3:TimeStamp>
 <Track3:WhiteBalanceRGB>(Binary data 22 bytes, use -b option to extract)</Track3:WhiteBalanceRGB>
 <Track3:TimeStamp>1.420498</Track3:TimeStamp>
 <Track3:ISOSpeeds>100</Track3:ISOSpeeds>
 <Track3:TimeStamp>1.407865</Track3:TimeStamp>
 <Track3:TimeStamp>1.387158</Track3:TimeStamp>
 <Track3:TimeStamp>1.407865</Track3:TimeStamp>
 <Track3:TimeStamp>1.407865</Track3:TimeStamp>
 <Track3:TimeStamp>1.412821</Track3:TimeStamp>
 <Track3:GPSMeasureMode>Unknown (0)</Track3:GPSMeasureMode>
 <Track3:GPSDateTime>2021:09:15 12:46:53.314</Track3:GPSDateTime>
 <Track3:GPSHPositioningError>99.99</Track3:GPSHPositioningError>
 <Track3:GPSLatitude>51 deg 18&#39; 21.66&quot; N</Track3:GPSLatitude>
 <Track3:GPSLongitude>0 deg 52&#39; 16.50&quot; W</Track3:GPSLongitude>
 <Track3:GPSAltitude>180.637 m</Track3:GPSAltitude>
 <Track3:GPSSpeed>0</Track3:GPSSpeed>
 <Track3:GPSSpeed3D>0</Track3:GPSSpeed3D>
 <Track3:TimeStamp>1.754192</Track3:TimeStamp>
 <Track3:TimeStamp>1.754192</Track3:TimeStamp>
 <Track3:TimeStamp>1.453858</Track3:TimeStamp>
 <Track3:TimeStamp>1.754192</Track3:TimeStamp>
 <Track3:SampleTime>0.20 s</Track3:SampleTime>
 <Track3:SampleDuration>0.03 s</Track3:SampleDuration>
 <Track3:DeviceName>GoPro Max</Track3:DeviceName>
 <Track3:TimeStamp>1.755203</Track3:TimeStamp>
 <Track3:CameraTemperature>26.439453125 C</Track3:CameraTemperature>
 <Track3:Accelerometer>(Binary data 53 bytes, use -b option to extract)</Track3:Accelerometer>
 <Track3:TimeStamp>1.755203</Track3:TimeStamp>
 <Track3:CameraTemperature>26.439453125 C</Track3:CameraTemperature>
 <Track3:Gyroscope>(Binary data 55 bytes, use -b option to extract)</Track3:Gyroscope>
 <Track3:TimeStamp>1.768337</Track3:TimeStamp>
 <Track3:Magnetometer>6 26 29</Track3:Magnetometer>
 <Track3:TimeStamp>1.754168</Track3:TimeStamp>
 <Track3:ExposureTimes>1/790</Track3:ExposureTimes>
 <Track3:TimeStamp>1.787558</Track3:TimeStamp>
 <Track3:ColorTemperatures>6104</Track3:ColorTemperatures>
 <Track3:TimeStamp>1.787558</Track3:TimeStamp>
 <Track3:WhiteBalanceRGB>(Binary data 23 bytes, use -b option to extract)</Track3:WhiteBalanceRGB>
 <Track3:TimeStamp>1.754168</Track3:TimeStamp>
 <Track3:ISOSpeeds>100</Track3:ISOSpeeds>
 <Track3:TimeStamp>1.71819</Track3:TimeStamp>
 <Track3:TimeStamp>1.787558</Track3:TimeStamp>
 <Track3:TimeStamp>1.71819</Track3:TimeStamp>
 <Track3:TimeStamp>1.71819</Track3:TimeStamp>
 <Track3:TimeStamp>1.773973</Track3:TimeStamp>
 <Track3:GPSMeasureMode>Unknown (0)</Track3:GPSMeasureMode>
 <Track3:GPSDateTime>2021:09:15 12:46:53.424</Track3:GPSDateTime>
 <Track3:GPSHPositioningError>99.99</Track3:GPSHPositioningError>
 <Track3:GPSLatitude>51 deg 18&#39; 21.60&quot; N</Track3:GPSLatitude>
 <Track3:GPSLongitude>0 deg 52&#39; 16.46&quot; W</Track3:GPSLongitude>
 <Track3:GPSAltitude>180.635 m</Track3:GPSAltitude>
 <Track3:GPSSpeed>0</Track3:GPSSpeed>
 <Track3:GPSSpeed3D>0</Track3:GPSSpeed3D>
 <Track3:TimeStamp>2.087858</Track3:TimeStamp>
 <Track3:TimeStamp>2.087858</Track3:TimeStamp>
 <Track3:TimeStamp>1.787525</Track3:TimeStamp>
 <Track3:TimeStamp>2.087858</Track3:TimeStamp>
 <Track3:SampleTime>0.23 s</Track3:SampleTime>
 <Track3:SampleDuration>0.03 s</Track3:SampleDuration>
 <Track3:DeviceName>GoPro Max</Track3:DeviceName>
 <Track3:TimeStamp>2.08915</Track3:TimeStamp>
 <Track3:CameraTemperature>26.4921875 C</Track3:CameraTemperature>
 <Track3:Accelerometer>(Binary data 55 bytes, use -b option to extract)</Track3:Accelerometer>
 <Track3:TimeStamp>2.08915</Track3:TimeStamp>
 <Track3:CameraTemperature>26.4921875 C</Track3:CameraTemperature>
 <Track3:Gyroscope>(Binary data 57 bytes, use -b option to extract)</Track3:Gyroscope>
 <Track3:TimeStamp>2.087295</Track3:TimeStamp>
 <Track3:Magnetometer>5 25 31</Track3:Magnetometer>
 <Track3:TimeStamp>2.087838</Track3:TimeStamp>
 <Track3:ExposureTimes>1/790</Track3:ExposureTimes>
 <Track3:TimeStamp>2.087858</Track3:TimeStamp>
 <Track3:ColorTemperatures>6104</Track3:ColorTemperatures>
 <Track3:TimeStamp>2.087858</Track3:TimeStamp>
 <Track3:WhiteBalanceRGB>(Binary data 23 bytes, use -b option to extract)</Track3:WhiteBalanceRGB>
 <Track3:TimeStamp>2.087838</Track3:TimeStamp>
 <Track3:ISOSpeeds>100</Track3:ISOSpeeds>
 <Track3:TimeStamp>2.151086</Track3:TimeStamp>
 <Track3:TimeStamp>2.087858</Track3:TimeStamp>
 <Track3:TimeStamp>2.151086</Track3:TimeStamp>
 <Track3:TimeStamp>2.151086</Track3:TimeStamp>
 <Track3:TimeStamp>2.13042</Track3:TimeStamp>
 <Track3:GPSMeasureMode>Unknown (0)</Track3:GPSMeasureMode>
 <Track3:GPSDateTime>2021:09:15 12:46:53.479</Track3:GPSDateTime>
 <Track3:GPSHPositioningError>99.99</Track3:GPSHPositioningError>
 <Track3:GPSLatitude>51 deg 18&#39; 21.62&quot; N</Track3:GPSLatitude>
 <Track3:GPSLongitude>0 deg 52&#39; 16.59&quot; W</Track3:GPSLongitude>
 <Track3:GPSAltitude>180.641 m</Track3:GPSAltitude>
 <Track3:GPSSpeed>0</Track3:GPSSpeed>
 <Track3:GPSSpeed3D>0</Track3:GPSSpeed3D>
 <Track3:TimeStamp>2.421525</Track3:TimeStamp>
 <Track3:TimeStamp>2.421525</Track3:TimeStamp>
 <Track3:TimeStamp>2.121191</Track3:TimeStamp>
 <Track3:TimeStamp>2.421525</Track3:TimeStamp>
 <Track3:SampleTime>0.27 s</Track3:SampleTime>
 <Track3:SampleDuration>0.03 s</Track3:SampleDuration>
 <Track3:DeviceName>GoPro Max</Track3:DeviceName>
 <Track3:TimeStamp>2.423068</Track3:TimeStamp>
 <Track3:CameraTemperature>26.55078125 C</Track3:CameraTemperature>
 <Track3:Accelerometer>(Binary data 56 bytes, use -b option to extract)</Track3:Accelerometer>
 <Track3:TimeStamp>2.423068</Track3:TimeStamp>
 <Track3:CameraTemperature>26.55078125 C</Track3:CameraTemperature>
 <Track3:Gyroscope>(Binary data 55 bytes, use -b option to extract)</Track3:Gyroscope>
 <Track3:TimeStamp>2.406247</Track3:TimeStamp>
 <Track3:Magnetometer>5 24 31</Track3:Magnetometer>
 <Track3:TimeStamp>2.421508</Track3:TimeStamp>
 <Track3:ExposureTimes>1/787</Track3:ExposureTimes>
 <Track3:TimeStamp>2.388158</Track3:TimeStamp>
 <Track3:ColorTemperatures>6043</Track3:ColorTemperatures>
 <Track3:TimeStamp>2.388158</Track3:TimeStamp>
 <Track3:WhiteBalanceRGB>(Binary data 19 bytes, use -b option to extract)</Track3:WhiteBalanceRGB>
 <Track3:TimeStamp>2.421508</Track3:TimeStamp>
 <Track3:ISOSpeeds>100</Track3:ISOSpeeds>
 <Track3:TimeStamp>2.464804</Track3:TimeStamp>
 <Track3:TimeStamp>2.388158</Track3:TimeStamp>
 <Track3:TimeStamp>2.464804</Track3:TimeStamp>
 <Track3:TimeStamp>2.464804</Track3:TimeStamp>
 <Track3:TimeStamp>2.385554</Track3:TimeStamp>
 <Track3:GPSMeasureMode>Unknown (0)</Track3:GPSMeasureMode>
 <Track3:GPSDateTime>2021:09:15 12:46:54.469</Track3:GPSDateTime>
 <Track3:GPSHPositioningError>99.99</Track3:GPSHPositioningError>
 <Track3:GPSLatitude>51 deg 18&#39; 21.67&quot; N</Track3:GPSLatitude>
 <Track3:GPSLongitude>0 deg 52&#39; 16.59&quot; W</Track3:GPSLongitude>
 <Track3:GPSAltitude>180.639 m</Track3:GPSAltitude>
 <Track3:GPSSpeed>0</Track3:GPSSpeed>
 <Track3:GPSSpeed3D>0</Track3:GPSSpeed3D>
 <Track3:TimeStamp>2.755192</Track3:TimeStamp>
 <Track3:TimeStamp>2.755192</Track3:TimeStamp>
 <Track3:TimeStamp>2.454858</Track3:TimeStamp>
 <Track3:TimeStamp>2.755192</Track3:TimeStamp>
 <Track3:SampleTime>0.30 s</Track3:SampleTime>
 <Track3:SampleDuration>0.03 s</Track3:SampleDuration>
 <Track3:DeviceName>GoPro Max</Track3:DeviceName>
 <Track3:TimeStamp>2.756994</Track3:TimeStamp>
 <Track3:CameraTemperature>26.52734375 C</Track3:CameraTemperature>
 <Track3:Accelerometer>(Binary data 54 bytes, use -b option to extract)</Track3:Accelerometer>
 <Track3:TimeStamp>2.756994</Track3:TimeStamp>
 <Track3:CameraTemperature>26.52734375 C</Track3:CameraTemperature>
 <Track3:Gyroscope>(Binary data 57 bytes, use -b option to extract)</Track3:Gyroscope>
 <Track3:TimeStamp>2.765068</Track3:TimeStamp>
 <Track3:Magnetometer>6 23 31</Track3:Magnetometer>
 <Track3:TimeStamp>2.755168</Track3:TimeStamp>
 <Track3:ExposureTimes>1/783</Track3:ExposureTimes>
 <Track3:TimeStamp>2.788558</Track3:TimeStamp>
 <Track3:ColorTemperatures>6043</Track3:ColorTemperatures>
 <Track3:TimeStamp>2.788558</Track3:TimeStamp>
 <Track3:WhiteBalanceRGB>(Binary data 19 bytes, use -b option to extract)</Track3:WhiteBalanceRGB>
 <Track3:TimeStamp>2.755168</Track3:TimeStamp>
 <Track3:ISOSpeeds>100</Track3:ISOSpeeds>
 <Track3:TimeStamp>2.779649</Track3:TimeStamp>
 <Track3:TimeStamp>2.788558</Track3:TimeStamp>
 <Track3:TimeStamp>2.779649</Track3:TimeStamp>
 <Track3:TimeStamp>2.779649</Track3:TimeStamp>
 <Track3:TimeStamp>2.752498</Track3:TimeStamp>
 <Track3:GPSMeasureMode>Unknown (0)</Track3:GPSMeasureMode>
 <Track3:GPSDateTime>2021:09:15 12:46:54.634</Track3:GPSDateTime>
 <Track3:GPSHPositioningError>99.99</Track3:GPSHPositioningError>
 <Track3:GPSLatitude>51 deg 18&#39; 21.78&quot; N</Track3:GPSLatitude>
 <Track3:GPSLongitude>0 deg 52&#39; 16.71&quot; W</Track3:GPSLongitude>
 <Track3:GPSAltitude>180.641 m</Track3:GPSAltitude>
 <Track3:GPSSpeed>0</Track3:GPSSpeed>
 <Track3:GPSSpeed3D>0</Track3:GPSSpeed3D>
 <Track3:TimeStamp>3.088858</Track3:TimeStamp>
 <Track3:TimeStamp>3.088858</Track3:TimeStamp>
 <Track3:TimeStamp>2.788525</Track3:TimeStamp>
 <Track3:TimeStamp>3.088858</Track3:TimeStamp>
 <Track3:SampleTime>0.33 s</Track3:SampleTime>
 <Track3:SampleDuration>0.03 s</Track3:SampleDuration>
 <Track3:DeviceName>GoPro Max</Track3:DeviceName>
 <Track3:TimeStamp>3.090918</Track3:TimeStamp>
 <Track3:CameraTemperature>26.52734375 C</Track3:CameraTemperature>
 <Track3:Accelerometer>(Binary data 53 bytes, use -b option to extract)</Track3:Accelerometer>
 <Track3:TimeStamp>3.090918</Track3:TimeStamp>
 <Track3:CameraTemperature>26.52734375 C</Track3:CameraTemperature>
 <Track3:Gyroscope>(Binary data 58 bytes, use -b option to extract)</Track3:Gyroscope>
 <Track3:TimeStamp>3.08402</Track3:TimeStamp>
 <Track3:Magnetometer>6 24 31</Track3:Magnetometer>
 <Track3:TimeStamp>3.088838</Track3:TimeStamp>
 <Track3:ExposureTimes>1/778</Track3:ExposureTimes>
 <Track3:TimeStamp>3.088858</Track3:TimeStamp>
 <Track3:ColorTemperatures>6013</Track3:ColorTemperatures>
 <Track3:TimeStamp>3.088858</Track3:TimeStamp>
 <Track3:WhiteBalanceRGB>(Binary data 25 bytes, use -b option to extract)</Track3:WhiteBalanceRGB>
 <Track3:TimeStamp>3.088838</Track3:TimeStamp>
 <Track3:ISOSpeeds>100</Track3:ISOSpeeds>
 <Track3:TimeStamp>3.094526</Track3:TimeStamp>
 <Track3:TimeStamp>3.088858</Track3:TimeStamp>
 <Track3:TimeStamp>3.094526</Track3:TimeStamp>
 <Track3:TimeStamp>3.094526</Track3:TimeStamp>
 <Track3:TimeStamp>3.054774</Track3:TimeStamp>
 <Track3:GPSMeasureMode>Unknown (0)</Track3:GPSMeasureMode>
 <Track3:GPSDateTime>2021:09:15 12:46:54.689</Track3:GPSDateTime>
 <Track3:GPSHPositioningError>99.99</Track3:GPSHPositioningError>
 <Track3:GPSLatitude>51 deg 18&#39; 21.81&quot; N</Track3:GPSLatitude>
 <Track3:GPSLongitude>0 deg 52&#39; 16.75&quot; W</Track3:GPSLongitude>
 <Track3:GPSAltitude>180.641 m</Track3:GPSAltitude>
 <Track3:GPSSpeed>0</Track3:GPSSpeed>
 <Track3:GPSSpeed3D>0</Track3:GPSSpeed3D>
 <Track3:TimeStamp>3.422525</Track3:TimeStamp>
 <Track3:TimeStamp>3.422525</Track3:TimeStamp>
 <Track3:TimeStamp>3.122191</Track3:TimeStamp>
 <Track3:TimeStamp>3.422525</Track3:TimeStamp>
 <Track3:SampleTime>0.37 s</Track3:SampleTime>
 <Track3:SampleDuration>0.03 s</Track3:SampleDuration>
 <Track3:DeviceName>GoPro Max</Track3:DeviceName>
 <Track3:TimeStamp>3.424781</Track3:TimeStamp>
 <Track3:CameraTemperature>26.58203125 C</Track3:CameraTemperature>
 <Track3:Accelerometer>(Binary data 53 bytes, use -b option to extract)</Track3:Accelerometer>
 <Track3:TimeStamp>3.424781</Track3:TimeStamp>
 <Track3:CameraTemperature>26.58203125 C</Track3:CameraTemperature>
 <Track3:Gyroscope>(Binary data 56 bytes, use -b option to extract)</Track3:Gyroscope>
 <Track3:TimeStamp>3.40298</Track3:TimeStamp>
 <Track3:Magnetometer>5 27 31</Track3:Magnetometer>
 <Track3:TimeStamp>3.422508</Track3:TimeStamp>
 <Track3:ExposureTimes>1/770</Track3:ExposureTimes>
 <Track3:TimeStamp>3.389158</Track3:TimeStamp>
 <Track3:ColorTemperatures>5963</Track3:ColorTemperatures>
 <Track3:TimeStamp>3.389158</Track3:TimeStamp>
 <Track3:WhiteBalanceRGB>(Binary data 35 bytes, use -b option to extract)</Track3:WhiteBalanceRGB>
 <Track3:TimeStamp>3.422508</Track3:TimeStamp>
 <Track3:ISOSpeeds>100</Track3:ISOSpeeds>
 <Track3:TimeStamp>3.409704</Track3:TimeStamp>
 <Track3:TimeStamp>3.389158</Track3:TimeStamp>
 <Track3:TimeStamp>3.409704</Track3:TimeStamp>
 <Track3:TimeStamp>3.409704</Track3:TimeStamp>
 <Track3:TimeStamp>3.418199</Track3:TimeStamp>
 <Track3:GPSMeasureMode>Unknown (0)</Track3:GPSMeasureMode>
 <Track3:GPSDateTime>2021:09:15 12:46:54.744</Track3:GPSDateTime>
 <Track3:GPSHPositioningError>99.99</Track3:GPSHPositioningError>
 <Track3:GPSLatitude>51 deg 22&#39; 21.31&quot; N</Track3:GPSLatitude>
 <Track3:GPSLongitude>0 deg 47&#39; 50.74&quot; W</Track3:GPSLongitude>
 <Track3:GPSAltitude>161.422 m</Track3:GPSAltitude>
 <Track3:GPSSpeed>0</Track3:GPSSpeed>
 <Track3:GPSSpeed3D>0</Track3:GPSSpeed3D>
 <Track3:TimeStamp>3.756192</Track3:TimeStamp>
 <Track3:TimeStamp>3.756192</Track3:TimeStamp>
 <Track3:TimeStamp>3.455858</Track3:TimeStamp>
 <Track3:TimeStamp>3.756192</Track3:TimeStamp>
 <Track3:SampleTime>0.40 s</Track3:SampleTime>
 <Track3:SampleDuration>0.03 s</Track3:SampleDuration>
 <Track3:DeviceName>GoPro Max</Track3:DeviceName>
 <Track3:TimeStamp>3.758676</Track3:TimeStamp>
 <Track3:CameraTemperature>26.54296875 C</Track3:CameraTemperature>
 <Track3:Accelerometer>(Binary data 54 bytes, use -b option to extract)</Track3:Accelerometer>
 <Track3:TimeStamp>3.758676</Track3:TimeStamp>
 <Track3:CameraTemperature>26.54296875 C</Track3:CameraTemperature>
 <Track3:Gyroscope>(Binary data 57 bytes, use -b option to extract)</Track3:Gyroscope>
 <Track3:TimeStamp>3.761801</Track3:TimeStamp>
 <Track3:Magnetometer>5 28 30</Track3:Magnetometer>
 <Track3:TimeStamp>3.756178</Track3:TimeStamp>
 <Track3:ExposureTimes>1/760</Track3:ExposureTimes>
 <Track3:TimeStamp>3.789558</Track3:TimeStamp>
 <Track3:ColorTemperatures>5923</Track3:ColorTemperatures>
 <Track3:TimeStamp>3.789558</Track3:TimeStamp>
 <Track3:WhiteBalanceRGB>(Binary data 21 bytes, use -b option to extract)</Track3:WhiteBalanceRGB>
 <Track3:TimeStamp>3.756178</Track3:TimeStamp>
 <Track3:ISOSpeeds>100</Track3:ISOSpeeds>
 <Track3:TimeStamp>3.723344</Track3:TimeStamp>
 <Track3:TimeStamp>3.789558</Track3:TimeStamp>
 <Track3:TimeStamp>3.723344</Track3:TimeStamp>
 <Track3:TimeStamp>3.723344</Track3:TimeStamp>
 <Track3:TimeStamp>3.716331</Track3:TimeStamp>
 <Track3:GPSMeasureMode>Unknown (0)</Track3:GPSMeasureMode>
 <Track3:GPSDateTime>2021:09:15 12:46:55.239</Track3:GPSDateTime>
 <Track3:GPSHPositioningError>99.99</Track3:GPSHPositioningError>
 <Track3:GPSLatitude>51 deg 18&#39; 57.51&quot; N</Track3:GPSLatitude>
 <Track3:GPSLongitude>0 deg 52&#39; 53.97&quot; W</Track3:GPSLongitude>
 <Track3:GPSAltitude>179.627 m</Track3:GPSAltitude>
 <Track3:GPSSpeed>0</Track3:GPSSpeed>
 <Track3:GPSSpeed3D>0</Track3:GPSSpeed3D>
 <Track3:TimeStamp>4.089858</Track3:TimeStamp>
 <Track3:TimeStamp>4.089858</Track3:TimeStamp>
 <Track3:TimeStamp>3.789525</Track3:TimeStamp>
 <Track3:TimeStamp>4.089858</Track3:TimeStamp>
 <Track3:SampleTime>0.43 s</Track3:SampleTime>
 <Track3:SampleDuration>0.03 s</Track3:SampleDuration>
 <Track3:DeviceName>GoPro Max</Track3:DeviceName>
 <Track3:TimeStamp>4.087621</Track3:TimeStamp>
 <Track3:CameraTemperature>26.591796875 C</Track3:CameraTemperature>
 <Track3:Accelerometer>(Binary data 53 bytes, use -b option to extract)</Track3:Accelerometer>
 <Track3:TimeStamp>4.087621</Track3:TimeStamp>
 <Track3:CameraTemperature>26.591796875 C</Track3:CameraTemperature>
 <Track3:Gyroscope>(Binary data 57 bytes, use -b option to extract)</Track3:Gyroscope>
 <Track3:TimeStamp>4.080753</Track3:TimeStamp>
 <Track3:Magnetometer>5 25 31</Track3:Magnetometer>
 <Track3:TimeStamp>4.089848</Track3:TimeStamp>
 <Track3:ExposureTimes>1/749</Track3:ExposureTimes>
 <Track3:TimeStamp>4.089858</Track3:TimeStamp>
 <Track3:ColorTemperatures>5833</Track3:ColorTemperatures>
 <Track3:TimeStamp>4.089858</Track3:TimeStamp>
 <Track3:WhiteBalanceRGB>(Binary data 25 bytes, use -b option to extract)</Track3:WhiteBalanceRGB>
 <Track3:TimeStamp>4.089848</Track3:TimeStamp>
 <Track3:ISOSpeeds>100</Track3:ISOSpeeds>
 <Track3:TimeStamp>4.034576</Track3:TimeStamp>
 <Track3:TimeStamp>4.089858</Track3:TimeStamp>
 <Track3:TimeStamp>4.034576</Track3:TimeStamp>
 <Track3:TimeStamp>4.034576</Track3:TimeStamp>
 <Track3:TimeStamp>4.069036</Track3:TimeStamp>
 <Track3:GPSMeasureMode>Unknown (0)</Track3:GPSMeasureMode>
 <Track3:GPSDateTime>2021:09:15 12:46:55.239</Track3:GPSDateTime>
 <Track3:GPSHPositioningError>99.99</Track3:GPSHPositioningError>
 <Track3:GPSLatitude>51 deg 19&#39; 51.92&quot; N</Track3:GPSLatitude>
 <Track3:GPSLongitude>0 deg 51&#39; 33.21&quot; W</Track3:GPSLongitude>
 <Track3:GPSAltitude>174.774 m</Track3:GPSAltitude>
 <Track3:GPSSpeed>0</Track3:GPSSpeed>
 <Track3:GPSSpeed3D>0</Track3:GPSSpeed3D>
 <Track3:TimeStamp>4.423525</Track3:TimeStamp>
 <Track3:TimeStamp>4.423525</Track3:TimeStamp>
 <Track3:TimeStamp>4.123191</Track3:TimeStamp>
 <Track3:TimeStamp>4.423525</Track3:TimeStamp>
 <Track3:SampleTime>0.47 s</Track3:SampleTime>
 <Track3:SampleDuration>0.03 s</Track3:SampleDuration>
 <Track3:DeviceName>GoPro Max</Track3:DeviceName>
 <Track3:TimeStamp>4.421549</Track3:TimeStamp>
 <Track3:CameraTemperature>26.556640625 C</Track3:CameraTemperature>
 <Track3:Accelerometer>(Binary data 56 bytes, use -b option to extract)</Track3:Accelerometer>
 <Track3:TimeStamp>4.421549</Track3:TimeStamp>
 <Track3:CameraTemperature>26.556640625 C</Track3:CameraTemperature>
 <Track3:Gyroscope>(Binary data 57 bytes, use -b option to extract)</Track3:Gyroscope>
 <Track3:TimeStamp>4.439583</Track3:TimeStamp>
 <Track3:Magnetometer>5 27 31</Track3:Magnetometer>
 <Track3:TimeStamp>4.423518</Track3:TimeStamp>
 <Track3:ExposureTimes>1/738</Track3:ExposureTimes>
 <Track3:TimeStamp>4.390158</Track3:TimeStamp>
 <Track3:ColorTemperatures>5803</Track3:ColorTemperatures>
 <Track3:TimeStamp>4.390158</Track3:TimeStamp>
 <Track3:WhiteBalanceRGB>(Binary data 27 bytes, use -b option to extract)</Track3:WhiteBalanceRGB>
 <Track3:TimeStamp>4.423518</Track3:TimeStamp>
 <Track3:ISOSpeeds>100</Track3:ISOSpeeds>
 <Track3:TimeStamp>4.455706</Track3:TimeStamp>
 <Track3:TimeStamp>4.390158</Track3:TimeStamp>
 <Track3:TimeStamp>4.455706</Track3:TimeStamp>
 <Track3:TimeStamp>4.455706</Track3:TimeStamp>
 <Track3:TimeStamp>4.418841</Track3:TimeStamp>
 <Track3:GPSMeasureMode>Unknown (0)</Track3:GPSMeasureMode>
 <Track3:GPSDateTime>2021:09:15 12:46:55.294</Track3:GPSDateTime>
 <Track3:GPSHPositioningError>99.99</Track3:GPSHPositioningError>
 <Track3:GPSLatitude>51 deg 23&#39; 29.17&quot; N</Track3:GPSLatitude>
 <Track3:GPSLongitude>0 deg 46&#39; 9.78&quot; W</Track3:GPSLongitude>
 <Track3:GPSAltitude>155.348 m</Track3:GPSAltitude>
 <Track3:GPSSpeed>0</Track3:GPSSpeed>
 <Track3:GPSSpeed3D>0</Track3:GPSSpeed3D>
 <Track3:TimeStamp>4.757192</Track3:TimeStamp>
 <Track3:TimeStamp>4.757192</Track3:TimeStamp>
 <Track3:TimeStamp>4.456858</Track3:TimeStamp>
 <Track3:TimeStamp>4.757192</Track3:TimeStamp>
 <Track3:SampleTime>0.50 s</Track3:SampleTime>
 <Track3:SampleDuration>0.03 s</Track3:SampleDuration>
 <Track3:DeviceName>GoPro Max</Track3:DeviceName>
 <Track3:TimeStamp>4.755475</Track3:TimeStamp>
 <Track3:CameraTemperature>26.544921875 C</Track3:CameraTemperature>
 <Track3:Accelerometer>(Binary data 53 bytes, use -b option to extract)</Track3:Accelerometer>
 <Track3:TimeStamp>4.755475</Track3:TimeStamp>
 <Track3:CameraTemperature>26.544921875 C</Track3:CameraTemperature>
 <Track3:Gyroscope>(Binary data 57 bytes, use -b option to extract)</Track3:Gyroscope>
 <Track3:TimeStamp>4.758543</Track3:TimeStamp>
 <Track3:Magnetometer>2 29 31</Track3:Magnetometer>
 <Track3:TimeStamp>4.757188</Track3:TimeStamp>
 <Track3:ExposureTimes>1/728</Track3:ExposureTimes>
 <Track3:TimeStamp>4.790558</Track3:TimeStamp>
 <Track3:ColorTemperatures>5742</Track3:ColorTemperatures>
 <Track3:TimeStamp>4.790558</Track3:TimeStamp>
 <Track3:WhiteBalanceRGB>(Binary data 23 bytes, use -b option to extract)</Track3:WhiteBalanceRGB>
 <Track3:TimeStamp>4.757188</Track3:TimeStamp>
 <Track3:ISOSpeeds>100</Track3:ISOSpeeds>
 <Track3:TimeStamp>4.76515</Track3:TimeStamp>
 <Track3:TimeStamp>4.790558</Track3:TimeStamp>
 <Track3:TimeStamp>4.76515</Track3:TimeStamp>
 <Track3:TimeStamp>4.76515</Track3:TimeStamp>
 <Track3:TimeStamp>4.769111</Track3:TimeStamp>
 <Track3:GPSMeasureMode>Unknown (0)</Track3:GPSMeasureMode>
 <Track3:GPSDateTime>2021:09:15 12:46:55.349</Track3:GPSDateTime>
 <Track3:GPSHPositioningError>99.99</Track3:GPSHPositioningError>
 <Track3:GPSLatitude>51 deg 23&#39; 29.24&quot; N</Track3:GPSLatitude>
 <Track3:GPSLongitude>0 deg 46&#39; 9.61&quot; W</Track3:GPSLongitude>
 <Track3:GPSAltitude>155.336 m</Track3:GPSAltitude>
 <Track3:GPSSpeed>0</Track3:GPSSpeed>
 <Track3:GPSSpeed3D>0</Track3:GPSSpeed3D>
 <Track3:TimeStamp>5.090858</Track3:TimeStamp>
 <Track3:TimeStamp>5.090858</Track3:TimeStamp>
 <Track3:TimeStamp>4.790525</Track3:TimeStamp>
 <Track3:TimeStamp>5.090858</Track3:TimeStamp>
 <Track3:SampleTime>0.53 s</Track3:SampleTime>
 <Track3:SampleDuration>0.03 s</Track3:SampleDuration>
 <Track3:DeviceName>GoPro Max</Track3:DeviceName>
 <Track3:TimeStamp>5.0894</Track3:TimeStamp>
 <Track3:CameraTemperature>26.548828125 C</Track3:CameraTemperature>
 <Track3:Accelerometer>(Binary data 51 bytes, use -b option to extract)</Track3:Accelerometer>
 <Track3:TimeStamp>5.0894</Track3:TimeStamp>
 <Track3:CameraTemperature>26.548828125 C</Track3:CameraTemperature>
 <Track3:Gyroscope>(Binary data 56 bytes, use -b option to extract)</Track3:Gyroscope>
 <Track3:TimeStamp>5.077503</Track3:TimeStamp>
 <Track3:Magnetometer>3 30 31</Track3:Magnetometer>
 <Track3:TimeStamp>5.090848</Track3:TimeStamp>
 <Track3:ExposureTimes>1/714</Track3:ExposureTimes>
 <Track3:TimeStamp>5.090858</Track3:TimeStamp>
 <Track3:ColorTemperatures>5742</Track3:ColorTemperatures>
 <Track3:TimeStamp>5.090858</Track3:TimeStamp>
 <Track3:WhiteBalanceRGB>(Binary data 22 bytes, use -b option to extract)</Track3:WhiteBalanceRGB>
 <Track3:TimeStamp>5.090848</Track3:TimeStamp>
 <Track3:ISOSpeeds>100</Track3:ISOSpeeds>
 <Track3:TimeStamp>5.08151</Track3:TimeStamp>
 <Track3:TimeStamp>5.090858</Track3:TimeStamp>
 <Track3:TimeStamp>5.08151</Track3:TimeStamp>
 <Track3:TimeStamp>5.08151</Track3:TimeStamp>
 <Track3:TimeStamp>5.105982</Track3:TimeStamp>
 <Track3:GPSMeasureMode>Unknown (0)</Track3:GPSMeasureMode>
 <Track3:GPSDateTime>2021:09:15 12:46:55.349</Track3:GPSDateTime>
 <Track3:GPSHPositioningError>99.99</Track3:GPSHPositioningError>
 <Track3:GPSLatitude>51 deg 22&#39; 25.34&quot; N</Track3:GPSLatitude>
 <Track3:GPSLongitude>0 deg 45&#39; 17.01&quot; W</Track3:GPSLongitude>
 <Track3:GPSAltitude>153.563 m</Track3:GPSAltitude>
 <Track3:GPSSpeed>0</Track3:GPSSpeed>
 <Track3:GPSSpeed3D>0</Track3:GPSSpeed3D>
 <Track3:TimeStamp>5.424525</Track3:TimeStamp>
 <Track3:TimeStamp>5.424525</Track3:TimeStamp>
 <Track3:TimeStamp>5.124191</Track3:TimeStamp>
 <Track3:TimeStamp>5.424525</Track3:TimeStamp>
 <Track3:SampleTime>0.57 s</Track3:SampleTime>
 <Track3:SampleDuration>0.03 s</Track3:SampleDuration>
 <Track3:DeviceName>GoPro Max</Track3:DeviceName>
 <Track3:TimeStamp>5.423325</Track3:TimeStamp>
 <Track3:CameraTemperature>26.61328125 C</Track3:CameraTemperature>
 <Track3:Accelerometer>(Binary data 52 bytes, use -b option to extract)</Track3:Accelerometer>
 <Track3:TimeStamp>5.423325</Track3:TimeStamp>
 <Track3:CameraTemperature>26.61328125 C</Track3:CameraTemperature>
 <Track3:Gyroscope>(Binary data 57 bytes, use -b option to extract)</Track3:Gyroscope>
 <Track3:TimeStamp>5.436333</Track3:TimeStamp>
 <Track3:Magnetometer>3 28 31</Track3:Magnetometer>
 <Track3:TimeStamp>5.424508</Track3:TimeStamp>
 <Track3:ExposureTimes>1/696</Track3:ExposureTimes>
 <Track3:TimeStamp>5.391158</Track3:TimeStamp>
 <Track3:ColorTemperatures>5682</Track3:ColorTemperatures>
 <Track3:TimeStamp>5.391158</Track3:TimeStamp>
 <Track3:WhiteBalanceRGB>(Binary data 22 bytes, use -b option to extract)</Track3:WhiteBalanceRGB>
 <Track3:TimeStamp>5.424508</Track3:TimeStamp>
 <Track3:ISOSpeeds>100</Track3:ISOSpeeds>
 <Track3:TimeStamp>5.393474</Track3:TimeStamp>
 <Track3:TimeStamp>5.391158</Track3:TimeStamp>
 <Track3:TimeStamp>5.393474</Track3:TimeStamp>
 <Track3:TimeStamp>5.393474</Track3:TimeStamp>
 <Track3:TimeStamp>5.440067</Track3:TimeStamp>
 <Track3:GPSMeasureMode>Unknown (0)</Track3:GPSMeasureMode>
 <Track3:GPSDateTime>2021:09:15 12:46:55.404</Track3:GPSDateTime>
 <Track3:GPSHPositioningError>99.99</Track3:GPSHPositioningError>
 <Track3:GPSLatitude>51 deg 22&#39; 25.15&quot; N</Track3:GPSLatitude>
 <Track3:GPSLongitude>0 deg 45&#39; 16.81&quot; W</Track3:GPSLongitude>
 <Track3:GPSAltitude>153.553 m</Track3:GPSAltitude>
 <Track3:GPSSpeed>0</Track3:GPSSpeed>
 <Track3:GPSSpeed3D>0</Track3:GPSSpeed3D>
 <Track3:TimeStamp>5.758192</Track3:TimeStamp>
 <Track3:TimeStamp>5.758192</Track3:TimeStamp>
 <Track3:TimeStamp>5.457858</Track3:TimeStamp>
 <Track3:TimeStamp>5.758192</Track3:TimeStamp>
 <Track3:SampleTime>0.60 s</Track3:SampleTime>
 <Track3:SampleDuration>0.03 s</Track3:SampleDuration>
 <Track3:DeviceName>GoPro Max</Track3:DeviceName>
 <Track3:TimeStamp>5.75725</Track3:TimeStamp>
 <Track3:CameraTemperature>26.537109375 C</Track3:CameraTemperature>
 <Track3:Accelerometer>(Binary data 55 bytes, use -b option to extract)</Track3:Accelerometer>
 <Track3:TimeStamp>5.75725</Track3:TimeStamp>
 <Track3:CameraTemperature>26.537109375 C</Track3:CameraTemperature>
 <Track3:Gyroscope>(Binary data 57 bytes, use -b option to extract)</Track3:Gyroscope>
 <Track3:TimeStamp>5.755293</Track3:TimeStamp>
 <Track3:Magnetometer>2 27 31</Track3:Magnetometer>
 <Track3:TimeStamp>5.758178</Track3:TimeStamp>
 <Track3:ExposureTimes>1/679</Track3:ExposureTimes>
 <Track3:TimeStamp>5.791558</Track3:TimeStamp>
 <Track3:ColorTemperatures>5682</Track3:ColorTemperatures>
 <Track3:TimeStamp>5.791558</Track3:TimeStamp>
 <Track3:WhiteBalanceRGB>(Binary data 22 bytes, use -b option to extract)</Track3:WhiteBalanceRGB>
 <Track3:TimeStamp>5.758178</Track3:TimeStamp>
 <Track3:ISOSpeeds>100</Track3:ISOSpeeds>
 <Track3:TimeStamp>5.708603</Track3:TimeStamp>
 <Track3:TimeStamp>5.791558</Track3:TimeStamp>
 <Track3:TimeStamp>5.708603</Track3:TimeStamp>
 <Track3:TimeStamp>5.708603</Track3:TimeStamp>
 <Track3:TimeStamp>5.770511</Track3:TimeStamp>
 <Track3:GPSMeasureMode>Unknown (0)</Track3:GPSMeasureMode>
 <Track3:GPSDateTime>2021:09:15 12:46:55.404</Track3:GPSDateTime>
 <Track3:GPSHPositioningError>99.99</Track3:GPSHPositioningError>
 <Track3:GPSLatitude>51 deg 21&#39; 45.77&quot; N</Track3:GPSLatitude>
 <Track3:GPSLongitude>0 deg 44&#39; 15.49&quot; W</Track3:GPSLongitude>
 <Track3:GPSAltitude>165.106 m</Track3:GPSAltitude>
 <Track3:GPSSpeed>0</Track3:GPSSpeed>
 <Track3:GPSSpeed3D>0</Track3:GPSSpeed3D>
 <Track3:TimeStamp>6.091858</Track3:TimeStamp>
 <Track3:TimeStamp>6.091858</Track3:TimeStamp>
 <Track3:TimeStamp>5.791525</Track3:TimeStamp>
 <Track3:TimeStamp>6.091858</Track3:TimeStamp>
 <Track3:SampleTime>0.63 s</Track3:SampleTime>
 <Track3:SampleDuration>0.03 s</Track3:SampleDuration>
 <Track3:DeviceName>GoPro Max</Track3:DeviceName>
 <Track3:TimeStamp>6.09117</Track3:TimeStamp>
 <Track3:CameraTemperature>26.591796875 C</Track3:CameraTemperature>
 <Track3:Accelerometer>(Binary data 56 bytes, use -b option to extract)</Track3:Accelerometer>
 <Track3:TimeStamp>6.09117</Track3:TimeStamp>
 <Track3:CameraTemperature>26.591796875 C</Track3:CameraTemperature>
 <Track3:Gyroscope>(Binary data 56 bytes, use -b option to extract)</Track3:Gyroscope>
 <Track3:TimeStamp>6.074254</Track3:TimeStamp>
 <Track3:Magnetometer>0 28 31</Track3:Magnetometer>
 <Track3:TimeStamp>6.091854</Track3:TimeStamp>
 <Track3:ExposureTimes>1/664</Track3:ExposureTimes>
 <Track3:TimeStamp>6.091858</Track3:TimeStamp>
 <Track3:ColorTemperatures>5682</Track3:ColorTemperatures>
 <Track3:TimeStamp>6.091858</Track3:TimeStamp>
 <Track3:WhiteBalanceRGB>(Binary data 20 bytes, use -b option to extract)</Track3:WhiteBalanceRGB>
 <Track3:TimeStamp>6.091854</Track3:TimeStamp>
 <Track3:ISOSpeeds>100</Track3:ISOSpeeds>
 <Track3:TimeStamp>6.119811</Track3:TimeStamp>
 <Track3:TimeStamp>6.091858</Track3:TimeStamp>
 <Track3:TimeStamp>6.119811</Track3:TimeStamp>
 <Track3:TimeStamp>6.119811</Track3:TimeStamp>
 <Track3:TimeStamp>6.095653</Track3:TimeStamp>
 <Track3:GPSMeasureMode>Unknown (0)</Track3:GPSMeasureMode>
 <Track3:GPSDateTime>2021:09:15 12:46:55.459</Track3:GPSDateTime>
 <Track3:GPSHPositioningError>99.99</Track3:GPSHPositioningError>
 <Track3:GPSLatitude>51 deg 21&#39; 17.62&quot; N</Track3:GPSLatitude>
 <Track3:GPSLongitude>0 deg 43&#39; 30.03&quot; W</Track3:GPSLongitude>
 <Track3:GPSAltitude>172.441 m</Track3:GPSAltitude>
 <Track3:GPSSpeed>0</Track3:GPSSpeed>
 <Track3:GPSSpeed3D>0</Track3:GPSSpeed3D>
 <Track3:TimeStamp>6.425525</Track3:TimeStamp>
 <Track3:TimeStamp>6.425525</Track3:TimeStamp>
 <Track3:TimeStamp>6.125191</Track3:TimeStamp>
 <Track3:TimeStamp>6.425525</Track3:TimeStamp>
 <Track3:SampleTime>0.67 s</Track3:SampleTime>
 <Track3:SampleDuration>0.03 s</Track3:SampleDuration>
 <Track3:DeviceName>GoPro Max</Track3:DeviceName>
 <Track3:TimeStamp>6.425091</Track3:TimeStamp>
 <Track3:CameraTemperature>26.5625 C</Track3:CameraTemperature>
 <Track3:Accelerometer>(Binary data 54 bytes, use -b option to extract)</Track3:Accelerometer>
 <Track3:TimeStamp>6.425091</Track3:TimeStamp>
 <Track3:CameraTemperature>26.5625 C</Track3:CameraTemperature>
 <Track3:Gyroscope>(Binary data 54 bytes, use -b option to extract)</Track3:Gyroscope>
 <Track3:TimeStamp>6.433077</Track3:TimeStamp>
 <Track3:Magnetometer>0 28 32</Track3:Magnetometer>
 <Track3:TimeStamp>6.425522</Track3:TimeStamp>
 <Track3:ExposureTimes>1/648</Track3:ExposureTimes>
 <Track3:TimeStamp>6.392158</Track3:TimeStamp>
 <Track3:ColorTemperatures>5682</Track3:ColorTemperatures>
 <Track3:TimeStamp>6.392158</Track3:TimeStamp>
 <Track3:WhiteBalanceRGB>(Binary data 20 bytes, use -b option to extract)</Track3:WhiteBalanceRGB>
 <Track3:TimeStamp>6.425522</Track3:TimeStamp>
 <Track3:ISOSpeeds>100</Track3:ISOSpeeds>
 <Track3:TimeStamp>6.426764</Track3:TimeStamp>
 <Track3:TimeStamp>6.392158</Track3:TimeStamp>
 <Track3:TimeStamp>6.426764</Track3:TimeStamp>
 <Track3:TimeStamp>6.426764</Track3:TimeStamp>
 <Track3:TimeStamp>6.421776</Track3:TimeStamp>
 <Track3:GPSMeasureMode>Unknown (0)</Track3:GPSMeasureMode>
 <Track3:GPSDateTime>2021:09:15 12:46:55.514</Track3:GPSDateTime>
 <Track3:GPSHPositioningError>99.99</Track3:GPSHPositioningError>
 <Track3:GPSLatitude>51 deg 21&#39; 17.66&quot; N</Track3:GPSLatitude>
 <Track3:GPSLongitude>0 deg 43&#39; 30.01&quot; W</Track3:GPSLongitude>
 <Track3:GPSAltitude>172.447 m</Track3:GPSAltitude>
 <Track3:GPSSpeed>0</Track3:GPSSpeed>
 <Track3:GPSSpeed3D>0</Track3:GPSSpeed3D>
 <Track3:TimeStamp>6.759192</Track3:TimeStamp>
 <Track3:TimeStamp>6.759192</Track3:TimeStamp>
 <Track3:TimeStamp>6.458858</Track3:TimeStamp>
 <Track3:TimeStamp>6.759192</Track3:TimeStamp>
 <Track3:SampleTime>0.70 s</Track3:SampleTime>
 <Track3:SampleDuration>0.03 s</Track3:SampleDuration>
 <Track3:DeviceName>GoPro Max</Track3:DeviceName>
 <Track3:TimeStamp>6.758996</Track3:TimeStamp>
 <Track3:CameraTemperature>26.580078125 C</Track3:CameraTemperature>
 <Track3:Accelerometer>(Binary data 55 bytes, use -b option to extract)</Track3:Accelerometer>
 <Track3:TimeStamp>6.758996</Track3:TimeStamp>
 <Track3:CameraTemperature>26.580078125 C</Track3:CameraTemperature>
 <Track3:Gyroscope>(Binary data 56 bytes, use -b option to extract)</Track3:Gyroscope>
 <Track3:TimeStamp>6.752041</Track3:TimeStamp>
 <Track3:Magnetometer>1 28 31</Track3:Magnetometer>
 <Track3:TimeStamp>6.759182</Track3:TimeStamp>
 <Track3:ExposureTimes>1/633</Track3:ExposureTimes>
 <Track3:TimeStamp>6.792558</Track3:TimeStamp>
 <Track3:ColorTemperatures>5682</Track3:ColorTemperatures>
 <Track3:TimeStamp>6.792558</Track3:TimeStamp>
 <Track3:WhiteBalanceRGB>(Binary data 20 bytes, use -b option to extract)</Track3:WhiteBalanceRGB>
 <Track3:TimeStamp>6.759182</Track3:TimeStamp>
 <Track3:ISOSpeeds>100</Track3:ISOSpeeds>
 <Track3:TimeStamp>6.739631</Track3:TimeStamp>
 <Track3:TimeStamp>6.792558</Track3:TimeStamp>
 <Track3:TimeStamp>6.739631</Track3:TimeStamp>
 <Track3:TimeStamp>6.739631</Track3:TimeStamp>
 <Track3:TimeStamp>6.74774</Track3:TimeStamp>
 <Track3:GPSMeasureMode>Unknown (0)</Track3:GPSMeasureMode>
 <Track3:GPSDateTime>2021:09:15 12:46:55.514</Track3:GPSDateTime>
 <Track3:GPSHPositioningError>99.99</Track3:GPSHPositioningError>
 <Track3:GPSLatitude>51 deg 21&#39; 17.65&quot; N</Track3:GPSLatitude>
 <Track3:GPSLongitude>0 deg 43&#39; 29.99&quot; W</Track3:GPSLongitude>
 <Track3:GPSAltitude>172.437 m</Track3:GPSAltitude>
 <Track3:GPSSpeed>0</Track3:GPSSpeed>
 <Track3:GPSSpeed3D>0</Track3:GPSSpeed3D>
 <Track3:TimeStamp>7.092858</Track3:TimeStamp>
 <Track3:TimeStamp>7.092858</Track3:TimeStamp>
 <Track3:TimeStamp>6.792525</Track3:TimeStamp>
 <Track3:TimeStamp>7.092858</Track3:TimeStamp>
 <Track3:SampleTime>0.73 s</Track3:SampleTime>
 <Track3:SampleDuration>0.03 s</Track3:SampleDuration>
 <Track3:DeviceName>GoPro Max</Track3:DeviceName>
 <Track3:TimeStamp>7.09289</Track3:TimeStamp>
 <Track3:CameraTemperature>26.572265625 C</Track3:CameraTemperature>
 <Track3:Accelerometer>(Binary data 54 bytes, use -b option to extract)</Track3:Accelerometer>
 <Track3:TimeStamp>7.09289</Track3:TimeStamp>
 <Track3:CameraTemperature>26.572265625 C</Track3:CameraTemperature>
 <Track3:Gyroscope>(Binary data 55 bytes, use -b option to extract)</Track3:Gyroscope>
 <Track3:TimeStamp>7.110867</Track3:TimeStamp>
 <Track3:Magnetometer>3 29 30</Track3:Magnetometer>
 <Track3:TimeStamp>7.092852</Track3:TimeStamp>
 <Track3:ExposureTimes>1/616</Track3:ExposureTimes>
 <Track3:TimeStamp>7.092858</Track3:TimeStamp>
 <Track3:ColorTemperatures>5682</Track3:ColorTemperatures>
 <Track3:TimeStamp>7.092858</Track3:TimeStamp>
 <Track3:WhiteBalanceRGB>(Binary data 20 bytes, use -b option to extract)</Track3:WhiteBalanceRGB>
 <Track3:TimeStamp>7.092852</Track3:TimeStamp>
 <Track3:ISOSpeeds>100</Track3:ISOSpeeds>
 <Track3:TimeStamp>7.037308</Track3:TimeStamp>
 <Track3:TimeStamp>7.092858</Track3:TimeStamp>
 <Track3:TimeStamp>7.037308</Track3:TimeStamp>
 <Track3:TimeStamp>7.037308</Track3:TimeStamp>
 <Track3:TimeStamp>7.082825</Track3:TimeStamp>
 <Track3:GPSMeasureMode>Unknown (0)</Track3:GPSMeasureMode>
 <Track3:GPSDateTime>2021:09:15 12:46:55.569</Track3:GPSDateTime>
 <Track3:GPSHPositioningError>99.99</Track3:GPSHPositioningError>
 <Track3:GPSLatitude>51 deg 21&#39; 17.68&quot; N</Track3:GPSLatitude>
 <Track3:GPSLongitude>0 deg 43&#39; 29.88&quot; W</Track3:GPSLongitude>
 <Track3:GPSAltitude>172.416 m</Track3:GPSAltitude>
 <Track3:GPSSpeed>0</Track3:GPSSpeed>
 <Track3:GPSSpeed3D>0</Track3:GPSSpeed3D>
 <Track3:TimeStamp>7.426525</Track3:TimeStamp>
 <Track3:TimeStamp>7.426525</Track3:TimeStamp>
 <Track3:TimeStamp>7.126191</Track3:TimeStamp>
 <Track3:TimeStamp>7.426525</Track3:TimeStamp>
 <Track3:SampleTime>0.77 s</Track3:SampleTime>
 <Track3:SampleDuration>0.03 s</Track3:SampleDuration>
 <Track3:DeviceName>GoPro Max</Track3:DeviceName>
 <Track3:TimeStamp>7.426813</Track3:TimeStamp>
 <Track3:CameraTemperature>26.568359375 C</Track3:CameraTemperature>
 <Track3:Accelerometer>(Binary data 55 bytes, use -b option to extract)</Track3:Accelerometer>
 <Track3:TimeStamp>7.426813</Track3:TimeStamp>
 <Track3:CameraTemperature>26.568359375 C</Track3:CameraTemperature>
 <Track3:Gyroscope>(Binary data 55 bytes, use -b option to extract)</Track3:Gyroscope>
 <Track3:TimeStamp>7.429824</Track3:TimeStamp>
 <Track3:Magnetometer>3 27 31</Track3:Magnetometer>
 <Track3:TimeStamp>7.426523</Track3:TimeStamp>
 <Track3:ExposureTimes>1/597</Track3:ExposureTimes>
 <Track3:TimeStamp>7.393158</Track3:TimeStamp>
 <Track3:ColorTemperatures>5682</Track3:ColorTemperatures>
 <Track3:TimeStamp>7.393158</Track3:TimeStamp>
 <Track3:WhiteBalanceRGB>(Binary data 20 bytes, use -b option to extract)</Track3:WhiteBalanceRGB>
 <Track3:TimeStamp>7.426523</Track3:TimeStamp>
 <Track3:ISOSpeeds>100</Track3:ISOSpeeds>
 <Track3:TimeStamp>7.437796</Track3:TimeStamp>
 <Track3:TimeStamp>7.393158</Track3:TimeStamp>
 <Track3:TimeStamp>7.437796</Track3:TimeStamp>
 <Track3:TimeStamp>7.437796</Track3:TimeStamp>
 <Track3:TimeStamp>7.417236</Track3:TimeStamp>
 <Track3:GPSMeasureMode>Unknown (0)</Track3:GPSMeasureMode>
 <Track3:GPSDateTime>2021:09:15 12:46:55.569</Track3:GPSDateTime>
 <Track3:GPSHPositioningError>99.99</Track3:GPSHPositioningError>
 <Track3:GPSLatitude>51 deg 21&#39; 17.61&quot; N</Track3:GPSLatitude>
 <Track3:GPSLongitude>0 deg 43&#39; 30.03&quot; W</Track3:GPSLongitude>
 <Track3:GPSAltitude>172.442 m</Track3:GPSAltitude>
 <Track3:GPSSpeed>0</Track3:GPSSpeed>
 <Track3:GPSSpeed3D>0</Track3:GPSSpeed3D>
 <Track3:TimeStamp>7.760192</Track3:TimeStamp>
 <Track3:TimeStamp>7.760192</Track3:TimeStamp>
 <Track3:TimeStamp>7.459858</Track3:TimeStamp>
 <Track3:TimeStamp>7.760192</Track3:TimeStamp>
 <Track3:SampleTime>0.80 s</Track3:SampleTime>
 <Track3:SampleDuration>0.03 s</Track3:SampleDuration>
 <Track3:DeviceName>GoPro Max</Track3:DeviceName>
 <Track3:TimeStamp>7.760731</Track3:TimeStamp>
 <Track3:CameraTemperature>26.6171875 C</Track3:CameraTemperature>
 <Track3:Accelerometer>(Binary data 55 bytes, use -b option to extract)</Track3:Accelerometer>
 <Track3:TimeStamp>7.760731</Track3:TimeStamp>
 <Track3:CameraTemperature>26.6171875 C</Track3:CameraTemperature>
 <Track3:Gyroscope>(Binary data 58 bytes, use -b option to extract)</Track3:Gyroscope>
 <Track3:TimeStamp>7.748783</Track3:TimeStamp>
 <Track3:Magnetometer>2 26 32</Track3:Magnetometer>
 <Track3:TimeStamp>7.76019</Track3:TimeStamp>
 <Track3:ExposureTimes>1/579</Track3:ExposureTimes>
 <Track3:TimeStamp>7.793558</Track3:TimeStamp>
 <Track3:ColorTemperatures>5682</Track3:ColorTemperatures>
 <Track3:TimeStamp>7.793558</Track3:TimeStamp>
 <Track3:WhiteBalanceRGB>(Binary data 20 bytes, use -b option to extract)</Track3:WhiteBalanceRGB>
 <Track3:TimeStamp>7.76019</Track3:TimeStamp>
 <Track3:ISOSpeeds>100</Track3:ISOSpeeds>
 <Track3:TimeStamp>7.742873</Track3:TimeStamp>
 <Track3:TimeStamp>7.793558</Track3:TimeStamp>
 <Track3:TimeStamp>7.742873</Track3:TimeStamp>
 <Track3:TimeStamp>7.742873</Track3:TimeStamp>
 <Track3:TimeStamp>7.745238</Track3:TimeStamp>
 <Track3:GPSMeasureMode>Unknown (0)</Track3:GPSMeasureMode>
 <Track3:GPSDateTime>2021:09:15 12:46:55.624</Track3:GPSDateTime>
 <Track3:GPSHPositioningError>99.99</Track3:GPSHPositioningError>
 <Track3:GPSLatitude>51 deg 21&#39; 17.59&quot; N</Track3:GPSLatitude>
 <Track3:GPSLongitude>0 deg 43&#39; 30.04&quot; W</Track3:GPSLongitude>
 <Track3:GPSAltitude>172.46 m</Track3:GPSAltitude>
 <Track3:GPSSpeed>0</Track3:GPSSpeed>
 <Track3:GPSSpeed3D>0</Track3:GPSSpeed3D>
 <Track3:TimeStamp>8.093858</Track3:TimeStamp>
 <Track3:TimeStamp>8.093858</Track3:TimeStamp>
 <Track3:TimeStamp>7.793525</Track3:TimeStamp>
 <Track3:TimeStamp>8.093858</Track3:TimeStamp>
 <Track3:SampleTime>0.83 s</Track3:SampleTime>
 <Track3:SampleDuration>0.03 s</Track3:SampleDuration>
 <Track3:DeviceName>GoPro Max</Track3:DeviceName>
 <Track3:TimeStamp>8.094641</Track3:TimeStamp>
 <Track3:CameraTemperature>26.591796875 C</Track3:CameraTemperature>
 <Track3:Accelerometer>(Binary data 55 bytes, use -b option to extract)</Track3:Accelerometer>
 <Track3:TimeStamp>8.094641</Track3:TimeStamp>
 <Track3:CameraTemperature>26.591796875 C</Track3:CameraTemperature>
 <Track3:Gyroscope>(Binary data 39 bytes, use -b option to extract)</Track3:Gyroscope>
 <Track3:TimeStamp>8.107616</Track3:TimeStamp>
 <Track3:Magnetometer>1 29 31</Track3:Magnetometer>
 <Track3:TimeStamp>8.093858</Track3:TimeStamp>
 <Track3:ExposureTimes>1/559</Track3:ExposureTimes>
 <Track3:TimeStamp>8.093858</Track3:TimeStamp>
 <Track3:ColorTemperatures>5682</Track3:ColorTemperatures>
 <Track3:TimeStamp>8.093858</Track3:TimeStamp>
 <Track3:WhiteBalanceRGB>(Binary data 22 bytes, use -b option to extract)</Track3:WhiteBalanceRGB>
 <Track3:TimeStamp>8.093858</Track3:TimeStamp>
 <Track3:ISOSpeeds>100</Track3:ISOSpeeds>
 <Track3:TimeStamp>8.154726</Track3:TimeStamp>
 <Track3:TimeStamp>8.093858</Track3:TimeStamp>
 <Track3:TimeStamp>8.154726</Track3:TimeStamp>
 <Track3:TimeStamp>8.154726</Track3:TimeStamp>
 <Track3:TimeStamp>8.125814</Track3:TimeStamp>
 <Track3:GPSMeasureMode>Unknown (0)</Track3:GPSMeasureMode>
 <Track3:GPSDateTime>2021:09:15 12:46:55.679</Track3:GPSDateTime>
 <Track3:GPSHPositioningError>99.99</Track3:GPSHPositioningError>
 <Track3:GPSLatitude>51 deg 21&#39; 17.65&quot; N</Track3:GPSLatitude>
 <Track3:GPSLongitude>0 deg 43&#39; 29.94&quot; W</Track3:GPSLongitude>
 <Track3:GPSAltitude>172.467 m</Track3:GPSAltitude>
 <Track3:GPSSpeed>0</Track3:GPSSpeed>
 <Track3:GPSSpeed3D>0</Track3:GPSSpeed3D>
 <Track3:TimeStamp>8.427525</Track3:TimeStamp>
 <Track3:TimeStamp>8.427525</Track3:TimeStamp>
 <Track3:TimeStamp>8.127191</Track3:TimeStamp>
 <Track3:TimeStamp>8.427525</Track3:TimeStamp>
 <Track3:SampleTime>0.87 s</Track3:SampleTime>
 <Track3:SampleDuration>0.03 s</Track3:SampleDuration>
 <Track3:DeviceName>GoPro Max</Track3:DeviceName>
 <Track3:TimeStamp>8.428548</Track3:TimeStamp>
 <Track3:CameraTemperature>26.607421875 C</Track3:CameraTemperature>
 <Track3:Accelerometer>(Binary data 51 bytes, use -b option to extract)</Track3:Accelerometer>
 <Track3:TimeStamp>8.428548</Track3:TimeStamp>
 <Track3:CameraTemperature>26.607421875 C</Track3:CameraTemperature>
 <Track3:Gyroscope>(Binary data 58 bytes, use -b option to extract)</Track3:Gyroscope>
 <Track3:TimeStamp>8.426575</Track3:TimeStamp>
 <Track3:Magnetometer>1 31 31</Track3:Magnetometer>
 <Track3:TimeStamp>8.427524</Track3:TimeStamp>
 <Track3:ExposureTimes>1/535</Track3:ExposureTimes>
 <Track3:TimeStamp>8.394158</Track3:TimeStamp>
 <Track3:ColorTemperatures>5622</Track3:ColorTemperatures>
 <Track3:TimeStamp>8.394158</Track3:TimeStamp>
 <Track3:WhiteBalanceRGB>(Binary data 29 bytes, use -b option to extract)</Track3:WhiteBalanceRGB>
 <Track3:TimeStamp>8.427524</Track3:TimeStamp>
 <Track3:ISOSpeeds>100</Track3:ISOSpeeds>
 <Track3:TimeStamp>8.473404</Track3:TimeStamp>
 <Track3:TimeStamp>8.394158</Track3:TimeStamp>
 <Track3:TimeStamp>8.473404</Track3:TimeStamp>
 <Track3:TimeStamp>8.473404</Track3:TimeStamp>
 <Track3:TimeStamp>8.458088</Track3:TimeStamp>
 <Track3:GPSMeasureMode>Unknown (0)</Track3:GPSMeasureMode>
 <Track3:GPSDateTime>2021:09:15 12:46:55.734</Track3:GPSDateTime>
 <Track3:GPSHPositioningError>99.99</Track3:GPSHPositioningError>
 <Track3:GPSLatitude>51 deg 21&#39; 17.58&quot; N</Track3:GPSLatitude>
 <Track3:GPSLongitude>0 deg 43&#39; 29.95&quot; W</Track3:GPSLongitude>
 <Track3:GPSAltitude>172.447 m</Track3:GPSAltitude>
 <Track3:GPSSpeed>0</Track3:GPSSpeed>
 <Track3:GPSSpeed3D>0</Track3:GPSSpeed3D>
 <Track3:TimeStamp>8.761192</Track3:TimeStamp>
 <Track3:TimeStamp>8.761192</Track3:TimeStamp>
 <Track3:TimeStamp>8.460858</Track3:TimeStamp>
 <Track3:TimeStamp>8.761192</Track3:TimeStamp>
 <Track3:SampleTime>0.90 s</Track3:SampleTime>
 <Track3:SampleDuration>0.03 s</Track3:SampleDuration>
 <Track3:DeviceName>GoPro Max</Track3:DeviceName>
 <Track3:TimeStamp>8.762466</Track3:TimeStamp>
 <Track3:CameraTemperature>26.607421875 C</Track3:CameraTemperature>
 <Track3:Accelerometer>(Binary data 53 bytes, use -b option to extract)</Track3:Accelerometer>
 <Track3:TimeStamp>8.762466</Track3:TimeStamp>
 <Track3:CameraTemperature>26.607421875 C</Track3:CameraTemperature>
 <Track3:Gyroscope>(Binary data 53 bytes, use -b option to extract)</Track3:Gyroscope>
 <Track3:TimeStamp>8.745535</Track3:TimeStamp>
 <Track3:Magnetometer>1 33 31</Track3:Magnetometer>
 <Track3:TimeStamp>8.761192</Track3:TimeStamp>
 <Track3:ExposureTimes>1/521</Track3:ExposureTimes>
 <Track3:TimeStamp>8.794558</Track3:TimeStamp>
 <Track3:ColorTemperatures>5562</Track3:ColorTemperatures>
 <Track3:TimeStamp>8.794558</Track3:TimeStamp>
 <Track3:WhiteBalanceRGB>(Binary data 19 bytes, use -b option to extract)</Track3:WhiteBalanceRGB>
 <Track3:TimeStamp>8.761192</Track3:TimeStamp>
 <Track3:ISOSpeeds>100</Track3:ISOSpeeds>
 <Track3:TimeStamp>8.794558</Track3:TimeStamp>
 <Track3:TimeStamp>8.794558</Track3:TimeStamp>
 <Track3:TimeStamp>8.794558</Track3:TimeStamp>
 <Track3:TimeStamp>8.794558</Track3:TimeStamp>
 <Track3:TimeStamp>8.735428</Track3:TimeStamp>
 <Track3:GPSMeasureMode>Unknown (0)</Track3:GPSMeasureMode>
 <Track3:GPSDateTime>2021:09:15 12:46:56.394</Track3:GPSDateTime>
 <Track3:GPSHPositioningError>99.99</Track3:GPSHPositioningError>
 <Track3:GPSLatitude>51 deg 21&#39; 17.55&quot; N</Track3:GPSLatitude>
 <Track3:GPSLongitude>0 deg 43&#39; 29.97&quot; W</Track3:GPSLongitude>
 <Track3:GPSAltitude>172.441 m</Track3:GPSAltitude>
 <Track3:GPSSpeed>0</Track3:GPSSpeed>
 <Track3:GPSSpeed3D>0</Track3:GPSSpeed3D>
 <Track3:TimeStamp>8.794525</Track3:TimeStamp>
 <Track3:TimeStamp>8.794525</Track3:TimeStamp>
 <Track3:TimeStamp>8.794525</Track3:TimeStamp>
 <Track3:TimeStamp>8.794525</Track3:TimeStamp>
 <Track4:TrackHeaderVersion>0</Track4:TrackHeaderVersion>
 <Track4:TrackCreateDate>2021:09:15 13:48:23</Track4:TrackCreateDate>
 <Track4:TrackModifyDate>2021:09:15 13:48:23</Track4:TrackModifyDate>
 <Track4:TrackID>4</Track4:TrackID>
 <Track4:TrackDuration>0.90 s</Track4:TrackDuration>
 <Track4:TrackLayer>0</Track4:TrackLayer>
 <Track4:TrackVolume>0.00%</Track4:TrackVolume>
 <Track4:MatrixStructure>1 0 0 0 1 0 0 0 1</Track4:MatrixStructure>
 <Track4:MediaHeaderVersion>0</Track4:MediaHeaderVersion>
 <Track4:MediaCreateDate>2021:09:15 13:48:23</Track4:MediaCreateDate>
 <Track4:MediaModifyDate>2021:09:15 13:48:23</Track4:MediaModifyDate>
 <Track4:MediaTimeScale>90000</Track4:MediaTimeScale>
 <Track4:MediaDuration>0.90 s</Track4:MediaDuration>
 <Track4:HandlerClass>Media Handler</Track4:HandlerClass>
 <Track4:HandlerType>NRT Metadata</Track4:HandlerType>
 <Track4:HandlerDescription>GoPro SOS  </Track4:HandlerDescription>
 <Track4:GenMediaVersion>0</Track4:GenMediaVersion>
 <Track4:GenFlags>0 0 0</Track4:GenFlags>
 <Track4:GenGraphicsMode>srcCopy</Track4:GenGraphicsMode>
 <Track4:GenOpColor>0 0 0</Track4:GenOpColor>
 <Track4:GenBalance>0</Track4:GenBalance>
 <Track4:MetaFormat>fdsc</Track4:MetaFormat>
 <Track4:SampleTime>0 s</Track4:SampleTime>
 <Track4:SampleDuration>0 s</Track4:SampleDuration>
 <Track4:FirmwareVersion>H19.03.02.00.00</Track4:FirmwareVersion>
 <Track4:SerialNumber>C33613B25523881</Track4:SerialNumber>
 <Track4:OtherSerialNumber>C3351324612139</Track4:OtherSerialNumber>
 <Track4:Model>GoPro Max</Track4:Model>
 <Composite:ImageSize>1920x1080</Composite:ImageSize>
 <Composite:Megapixels>2.1</Composite:Megapixels>
 <Composite:AvgBitrate>65.3 Mbps</Composite:AvgBitrate>
 <Composite:Rotation>0</Composite:Rotation>
 <Composite:GPSPosition>51 deg 18&#39; 19.56&quot; N, 0 deg 51&#39; 56.24&quot; W</Composite:GPSPosition>
</rdf:Description>
</rdf:RDF>
